uart_pwm_project/rtl/rx_buffer.v
// rx_buffer.v
// Buffer circular para UART RX con 32 bytes de profundidad

module rx_buffer #(
    parameter DEPTH = 32,
    parameter WIDTH = 8
)(
    input  wire              clk,
    input  wire              rst,
    input  wire              wr_en,
    input  wire [WIDTH-1:0]  wr_data,
    input  wire              rd_en,
    output reg  [WIDTH-1:0]  rd_data,
    output wire              full,
    output wire              empty,
    output reg               end_of_str // se activa al recibir '\n' (0x0A)
);

    reg [WIDTH-1:0] mem [0:DEPTH-1];
    reg [$clog2(DEPTH):0] wr_ptr, rd_ptr, count;

    assign full  = (count == DEPTH);
    assign empty = (count == 0);

    always @(posedge clk or posedge rst) begin
        if (rst) begin
            wr_ptr <= 0;
            rd_ptr <= 0;
            count  <= 0;
            end_of_str <= 0;
        end else begin
            end_of_str <= 0;
            if (wr_en && !full) begin
                mem[wr_ptr] <= wr_data;
                wr_ptr <= wr_ptr + 1;
                count  <= count + 1;
                if (wr_data == 8'h0A) // detecta fin de string
                    end_of_str <= 1;
            end
            if (rd_en && !empty) begin
                rd_data <= mem[rd_ptr];
                rd_ptr  <= rd_ptr + 1;
                count   <= count - 1;
            end
        end
    end

endmodule

uart_pwm_project/tb/tb_rx_buffer.v
`timescale 1ns/1ps

module tb_rx_buffer;

    // Señales
    reg clk;
    reg rst;
    reg wr_en;
    reg [7:0] wr_data;
    reg rd_en;
    wire [7:0] rd_data;
    wire full;
    wire empty;
    wire end_of_str;

    // DUT
    rx_buffer #(.DEPTH(32), .WIDTH(8)) dut (
        .clk(clk),
        .rst(rst),
        .wr_en(wr_en),
        .wr_data(wr_data),
        .rd_en(rd_en),
        .rd_data(rd_data),
        .full(full),
        .empty(empty),
        .end_of_str(end_of_str)
    );

    // Clock
    initial clk = 0;
    always #5 clk = ~clk; // 100 MHz

    // Estímulos
    initial begin
        $dumpfile("wave_rx_buffer.vcd");
        $dumpvars(0, tb_rx_buffer);

        // Reset
        rst = 1;
        wr_en = 0; rd_en = 0; wr_data = 0;
        #20;
        rst = 0;

        // Escribir algunos bytes
        write_byte("H");
        write_byte("O");
        write_byte("L");
        write_byte("A");
        write_byte("\n");  // genera end_of_str
        #20;

        // Leer todos los bytes
        repeat (5) begin
            read_byte();
        end

        #50;
        $finish;
    end

    // Task: escribir un byte en el buffer
    task write_byte(input [7:0] b);
    begin
        @(posedge clk);
        wr_data <= b;
        wr_en   <= 1;
        @(posedge clk);
        wr_en   <= 0;
    end
    endtask

    // Task: leer un byte del buffer
    task read_byte;
    begin
        @(posedge clk);
        rd_en <= 1;
        @(posedge clk);
        rd_en <= 0;
        $display("Leído: %c (0x%0h)", rd_data, rd_data);
    end
    endtask

endmodule

uart_pwm_project/sim/wave_rx_buffer.vcd
$date
	Fri Oct 03 21:20:25 2025
$end
$version
	Icarus Verilog
$end
$timescale
	1ps
$end
$scope module tb_rx_buffer $end
$var wire 8 ! rd_data [7:0] $end
$var wire 1 " full $end
$var wire 1 # end_of_str $end
$var wire 1 $ empty $end
$var reg 1 % clk $end
$var reg 1 & rd_en $end
$var reg 1 ' rst $end
$var reg 8 ( wr_data [7:0] $end
$var reg 1 ) wr_en $end
$scope module dut $end
$var wire 1 % clk $end
$var wire 1 & rd_en $end
$var wire 1 ' rst $end
$var wire 8 * wr_data [7:0] $end
$var wire 1 ) wr_en $end
$var wire 1 " full $end
$var wire 1 $ empty $end
$var reg 6 + count [5:0] $end
$var reg 1 # end_of_str $end
$var reg 8 , rd_data [7:0] $end
$var reg 6 - rd_ptr [5:0] $end
$var reg 6 . wr_ptr [5:0] $end
$upscope $end
$scope task read_byte $end
$upscope $end
$scope task write_byte $end
$var reg 8 / b [7:0] $end
$upscope $end
$upscope $end
$enddefinitions $end
#0
$dumpvars
bx /
b0 .
b0 -
bx ,
b0 +
b0 *
0)
b0 (
1'
0&
0%
1$
0#
0"
bx !
$end
#5000
1%
#10000
0%
#15000
1%
#20000
0%
b1001000 /
0'
#25000
1)
b1001000 (
b1001000 *
1%
#30000
0%
#35000
0$
b1 +
b1 .
0)
b1001111 /
1%
#40000
0%
#45000
1)
b1001111 (
b1001111 *
1%
#50000
0%
#55000
b10 +
b10 .
0)
b1001100 /
1%
#60000
0%
#65000
1)
b1001100 (
b1001100 *
1%
#70000
0%
#75000
b11 +
b11 .
0)
b1000001 /
1%
#80000
0%
#85000
1)
b1000001 (
b1000001 *
1%
#90000
0%
#95000
b100 +
b100 .
0)
b1010 /
1%
#100000
0%
#105000
1)
b1010 (
b1010 *
1%
#110000
0%
#115000
1#
b101 +
b101 .
0)
1%
#120000
0%
#125000
0#
1%
#130000
0%
#135000
1&
1%
#140000
0%
#145000
b100 +
b1 -
b1001000 !
b1001000 ,
0&
1%
#150000
0%
#155000
1&
1%
#160000
0%
#165000
b11 +
b10 -
b1001111 !
b1001111 ,
0&
1%
#170000
0%
#175000
1&
1%
#180000
0%
#185000
b10 +
b11 -
b1001100 !
b1001100 ,
0&
1%
#190000
0%
#195000
1&
1%
#200000
0%
#205000
b1 +
b100 -
b1000001 !
b1000001 ,
0&
1%
#210000
0%
#215000
1&
1%
#220000
0%
#225000
1$
b0 +
b101 -
b1010 !
b1010 ,
0&
1%
