Knight_Rider/src/counter4.v
module counter4 (
    input clk,
    input reset,
    input enable,
    input dir,              // 0 = ascendente, 1 = descendente
    output reg [3:0] count
);
    always @(posedge clk or posedge reset) begin
        if (reset)
            count <= 4'b0000;
        else if (enable) begin
            if (!dir) begin
                if (count < 4'd7) count <= count + 1;
                else count <= count; // saturación en 7
            end else begin
                if (count > 0) count <= count - 1;
                else count <= count; // saturación en 0
            end
        end
    end
endmodule

Knight_Rider/tb/tb_counter4.v
`timescale 1ns/1ps
module tb_counter4;
    reg clk, reset, enable, dir;
    wire [3:0] count;

    counter4 uut (
        .clk(clk),
        .reset(reset),
        .enable(enable),
        .dir(dir),
        .count(count)
    );

    initial begin
        $dumpfile("../waves/counter4.vcd");
        $dumpvars(0, tb_counter4);

        clk = 0; reset = 1; enable = 0; dir = 0;
        #10 reset = 0; enable = 1;

        // Conteo ascendente
        dir = 0;
        #100;

        // Conteo descendente
        dir = 1;
        #100;

        // Reinicio
        reset = 1;
        #10 reset = 0;

        #50 $finish;
    end

    always #5 clk = ~clk; // reloj
endmodule

Knight_Rider/waves/counter4.vcd
$date
	Thu Sep 11 11:22:22 2025
$end
$version
	Icarus Verilog
$end
$timescale
	1ps
$end
$scope module tb_counter4 $end
$var wire 4 ! count [3:0] $end
$var reg 1 " clk $end
$var reg 1 # dir $end
$var reg 1 $ enable $end
$var reg 1 % reset $end
$scope module uut $end
$var wire 1 " clk $end
$var wire 1 # dir $end
$var wire 1 $ enable $end
$var wire 1 % reset $end
$var reg 4 & count [3:0] $end
$upscope $end
$upscope $end
$enddefinitions $end
#0
$dumpvars
b0 &
1%
0$
0#
0"
b0 !
$end
#5000
1"
#10000
0"
1$
0%
#15000
b1 !
b1 &
1"
#20000
0"
#25000
b10 !
b10 &
1"
#30000
0"
#35000
b11 !
b11 &
1"
#40000
0"
#45000
b100 !
b100 &
1"
#50000
0"
#55000
b101 !
b101 &
1"
#60000
0"
#65000
b110 !
b110 &
1"
#70000
0"
#75000
b111 !
b111 &
1"
#80000
0"
#85000
1"
#90000
0"
#95000
1"
#100000
0"
#105000
1"
#110000
0"
1#
#115000
b110 !
b110 &
1"
#120000
0"
#125000
b101 !
b101 &
1"
#130000
0"
#135000
b100 !
b100 &
1"
#140000
0"
#145000
b11 !
b11 &
1"
#150000
0"
#155000
b10 !
b10 &
1"
#160000
0"
#165000
b1 !
b1 &
1"
#170000
0"
#175000
b0 !
b0 &
1"
#180000
0"
#185000
1"
#190000
0"
#195000
1"
#200000
0"
#205000
1"
#210000
0"
1%
#215000
1"
#220000
0"
0%
