Knight_Rider/src/decoder3to8.v
module decoder3to8 (
    input  [2:0] sel,
    output reg [7:0] out
);
    always @(*) begin
        out = 8'b00000000;
        out[sel] = 1'b1;
    end
endmodule

Knight_Rider/tb/tb_decoder3to8.v
`timescale 1ns/1ps
module tb_decoder3to8;
    reg [2:0] sel;
    wire [7:0] out;

    decoder3to8 uut (
        .sel(sel),
        .out(out)
    );

    initial begin
        $dumpfile("../waves/decoder3to8.vcd");
        $dumpvars(0, tb_decoder3to8);

        sel = 3'b000;
        repeat (8) begin
            #10 sel = sel + 1;
        end
        #20 $finish;
    end
endmodule

Knight_Rider/waves/decoder3to8.vcd
$date
	Thu Sep 11 11:22:37 2025
$end
$version
	Icarus Verilog
$end
$timescale
	1ps
$end
$scope module tb_decoder3to8 $end
$var wire 8 ! out [7:0] $end
$var reg 3 " sel [2:0] $end
$scope module uut $end
$var wire 3 # sel [2:0] $end
$var reg 8 $ out [7:0] $end
$upscope $end
$upscope $end
$enddefinitions $end
#0
$dumpvars
b1 $
b0 #
b0 "
b1 !
$end
#10000
b10 !
b10 $
b1 "
b1 #
#20000
b100 !
b100 $
b10 "
b10 #
#30000
b1000 !
b1000 $
b11 "
b11 #
#40000
b10000 !
b10000 $
b100 "
b100 #
#50000
b100000 !
b100000 $
b101 "
b101 #
#60000
b1000000 !
b1000000 $
b110 "
b110 #
#70000
b10000000 !
b10000000 $
b111 "
b111 #
#80000
b1 !
b1 $
b0 "
b0 #
