Knight_Rider/src/decoder3to8.v
module decoder3to8 (
    input  [2:0] sel,
    output reg [7:0] out
);
    always @(*) begin
        out = 8'b00000000;
        out[sel] = 1'b1;
    end
endmodule

Knight_Rider/src/fsm2.v
module fsm2 (
    input clk,
    input reset,
    input [3:0] count,
    output reg dir
);
    // Estados
    parameter LEFT  = 1'b0;
    parameter RIGHT = 1'b1;

    reg state, next_state;

    always @(posedge clk or posedge reset) begin
        if (reset)
            state <= LEFT;
        else
            state <= next_state;
    end

    always @(*) begin
        case (state)
            LEFT:  next_state = (count == 4'd7) ? RIGHT : LEFT;
            RIGHT: next_state = (count == 4'd0) ? LEFT  : RIGHT;
            default: next_state = LEFT;
        endcase
    end

    always @(*) begin
        case (state)
            LEFT:  dir = 1'b0;
            RIGHT: dir = 1'b1;
            default: dir = 1'b0;
        endcase
    end
endmodule

Knight_Rider/src/counter4.v
module counter4 (
    input clk,
    input reset,
    input enable,
    input dir,              // 0 = ascendente, 1 = descendente
    output reg [3:0] count
);
    always @(posedge clk or posedge reset) begin
        if (reset)
            count <= 4'b0000;
        else if (enable) begin
            if (!dir) begin
                if (count < 4'd7) count <= count + 1;
                else count <= count; // saturación en 7
            end else begin
                if (count > 0) count <= count - 1;
                else count <= count; // saturación en 0
            end
        end
    end
endmodule

Knight_Rider/src/knight_rider.v
module knight_rider (
    input clk,
    input reset,
    input enable,
    output [7:0] leds
);
    wire [3:0] count;
    wire dir;

    counter4 U1 (
        .clk(clk),
        .reset(reset),
        .enable(enable),
        .dir(dir),
        .count(count)
    );

    fsm2 U2 (
        .clk(clk),
        .reset(reset),
        .count(count),
        .dir(dir)
    );

    decoder3to8 U3 (
        .sel(count[2:0]),
        .out(leds)
    );
endmodule

Knight_Rider/tb/tb_knight_rider.v
`timescale 1ns/1ps
module tb_knight_rider;
    reg clk, reset, enable;
    wire [7:0] leds;

    knight_rider uut (
        .clk(clk),
        .reset(reset),
        .enable(enable),
        .leds(leds)
    );

    initial begin
        $dumpfile("../waves/knight_rider.vcd");
        $dumpvars(0, tb_knight_rider);

        clk = 0; reset = 1; enable = 0;
        #10 reset = 0; enable = 1;

        #500 $finish;
    end

    always #5 clk = ~clk; // reloj
endmodule

Knight_Rider/waves/knight_rider.vcd
$date
	Thu Sep 11 11:24:43 2025
$end
$version
	Icarus Verilog
$end
$timescale
	1ps
$end
$scope module tb_knight_rider $end
$var wire 8 ! leds [7:0] $end
$var reg 1 " clk $end
$var reg 1 # enable $end
$var reg 1 $ reset $end
$scope module uut $end
$var wire 1 " clk $end
$var wire 1 # enable $end
$var wire 1 $ reset $end
$var wire 8 % leds [7:0] $end
$var wire 1 & dir $end
$var wire 4 ' count [3:0] $end
$scope module U1 $end
$var wire 1 " clk $end
$var wire 1 # enable $end
$var wire 1 $ reset $end
$var wire 1 & dir $end
$var reg 4 ( count [3:0] $end
$upscope $end
$scope module U2 $end
$var wire 1 " clk $end
$var wire 4 ) count [3:0] $end
$var wire 1 $ reset $end
$var reg 1 & dir $end
$var reg 1 * next_state $end
$var reg 1 + state $end
$upscope $end
$scope module U3 $end
$var wire 3 , sel [2:0] $end
$var reg 8 - out [7:0] $end
$upscope $end
$upscope $end
$upscope $end
$enddefinitions $end
#0
$dumpvars
b1 -
b0 ,
0+
0*
b0 )
b0 (
b0 '
0&
b1 %
1$
0#
0"
b1 !
$end
#5000
1"
#10000
0"
1#
0$
#15000
b10 !
b10 %
b10 -
b1 ,
b1 '
b1 (
b1 )
1"
#20000
0"
#25000
b100 !
b100 %
b100 -
b10 ,
b10 '
b10 (
b10 )
1"
#30000
0"
#35000
b1000 !
b1000 %
b1000 -
b11 ,
b11 '
b11 (
b11 )
1"
#40000
0"
#45000
b10000 !
b10000 %
b10000 -
b100 ,
b100 '
b100 (
b100 )
1"
#50000
0"
#55000
b100000 !
b100000 %
b100000 -
b101 ,
b101 '
b101 (
b101 )
1"
#60000
0"
#65000
b1000000 !
b1000000 %
b1000000 -
b110 ,
b110 '
b110 (
b110 )
1"
#70000
0"
#75000
b10000000 !
b10000000 %
b10000000 -
1*
b111 ,
b111 '
b111 (
b111 )
1"
#80000
0"
#85000
1&
1+
1"
#90000
0"
#95000
b1000000 !
b1000000 %
b1000000 -
b110 ,
b110 '
b110 (
b110 )
1"
#100000
0"
#105000
b100000 !
b100000 %
b100000 -
b101 ,
b101 '
b101 (
b101 )
1"
#110000
0"
#115000
b10000 !
b10000 %
b10000 -
b100 ,
b100 '
b100 (
b100 )
1"
#120000
0"
#125000
b1000 !
b1000 %
b1000 -
b11 ,
b11 '
b11 (
b11 )
1"
#130000
0"
#135000
b100 !
b100 %
b100 -
b10 ,
b10 '
b10 (
b10 )
1"
#140000
0"
#145000
b10 !
b10 %
b10 -
b1 ,
b1 '
b1 (
b1 )
1"
#150000
0"
#155000
b1 !
b1 %
b1 -
0*
b0 ,
b0 '
b0 (
b0 )
1"
#160000
0"
#165000
0&
0+
1"
#170000
0"
#175000
b10 !
b10 %
b10 -
b1 ,
b1 '
b1 (
b1 )
1"
#180000
0"
#185000
b100 !
b100 %
b100 -
b10 ,
b10 '
b10 (
b10 )
1"
#190000
0"
#195000
b1000 !
b1000 %
b1000 -
b11 ,
b11 '
b11 (
b11 )
1"
#200000
0"
#205000
b10000 !
b10000 %
b10000 -
b100 ,
b100 '
b100 (
b100 )
1"
#210000
0"
#215000
b100000 !
b100000 %
b100000 -
b101 ,
b101 '
b101 (
b101 )
1"
#220000
0"
#225000
b1000000 !
b1000000 %
b1000000 -
b110 ,
b110 '
b110 (
b110 )
1"
#230000
0"
#235000
b10000000 !
b10000000 %
b10000000 -
1*
b111 ,
b111 '
b111 (
b111 )
1"
#240000
0"
#245000
1&
1+
1"
#250000
0"
#255000
b1000000 !
b1000000 %
b1000000 -
b110 ,
b110 '
b110 (
b110 )
1"
#260000
0"
#265000
b100000 !
b100000 %
b100000 -
b101 ,
b101 '
b101 (
b101 )
1"
#270000
0"
#275000
b10000 !
b10000 %
b10000 -
b100 ,
b100 '
b100 (
b100 )
1"
#280000
0"
#285000
b1000 !
b1000 %
b1000 -
b11 ,
b11 '
b11 (
b11 )
1"
#290000
0"
#295000
b100 !
b100 %
b100 -
b10 ,
b10 '
b10 (
b10 )
1"
#300000
0"
#305000
b10 !
b10 %
b10 -
b1 ,
b1 '
b1 (
b1 )
1"
#310000
0"
#315000
b1 !
b1 %
b1 -
0*
b0 ,
b0 '
b0 (
b0 )
1"
#320000
0"
#325000
0&
0+
1"
#330000
0"
#335000
b10 !
b10 %
b10 -
b1 ,
b1 '
b1 (
b1 )
1"
#340000
0"
#345000
b100 !
b100 %
b100 -
b10 ,
b10 '
b10 (
b10 )
1"
#350000
0"
#355000
b1000 !
b1000 %
b1000 -
b11 ,
b11 '
b11 (
b11 )
1"
#360000
0"
#365000
b10000 !
b10000 %
b10000 -
b100 ,
b100 '
b100 (
b100 )
1"
#370000
0"
#375000
b100000 !
b100000 %
b100000 -
b101 ,
b101 '
b101 (
b101 )
1"
#380000
0"
#385000
b1000000 !
b1000000 %
b1000000 -
b110 ,
b110 '
b110 (
b110 )
1"
#390000
0"
#395000
b10000000 !
b10000000 %
b10000000 -
1*
b111 ,
b111 '
b111 (
b111 )
1"
#400000
0"
#405000
1&
1+
1"
#410000
0"
#415000
b1000000 !
b1000000 %
b1000000 -
b110 ,
b110 '
b110 (
b110 )
1"
#420000
0"
#425000
b100000 !
b100000 %
b100000 -
b101 ,
b101 '
b101 (
b101 )
1"
#430000
0"
#435000
b10000 !
b10000 %
b10000 -
b100 ,
b100 '
b100 (
b100 )
1"
#440000
0"
#445000
b1000 !
b1000 %
b1000 -
b11 ,
b11 '
b11 (
b11 )
1"
#450000
0"
#455000
b100 !
b100 %
b100 -
b10 ,
b10 '
b10 (
b10 )
1"
#460000
0"
#465000
b10 !
b10 %
b10 -
b1 ,
b1 '
b1 (
b1 )
1"
#470000
0"
#475000
b1 !
b1 %
b1 -
0*
b0 ,
b0 '
b0 (
b0 )
1"
#480000
0"
#485000
0&
0+
1"
#490000
0"
#495000
b10 !
b10 %
b10 -
b1 ,
b1 '
b1 (
b1 )
1"
#500000
0"
#505000
b100 !
b100 %
b100 -
b10 ,
b10 '
b10 (
b10 )
1"
